glass/__init__.py
glass/_helpers.py
glass/app.py
glass/config.py
glass/constant.py
glass/cookie.py
glass/exception.py
glass/highlight.py
glass/http.py
glass/requests.py
glass/response.py
glass/routing.py
glass/server.py
glass/sessions.py
glass/templatetags.py
glass/templating.py
glass/types.py
glass/utils.py
glass/template/__init__.py
glass/template/filters.py
glass/template/main.py
glass/template/nodes.py
glass/template/parser.py
glass/template/utils.py
glass_web-0.0.7.dist-info/LICENSE
glass_web-0.0.7.dist-info/METADATA
glass_web-0.0.7.dist-info/WHEEL
glass_web-0.0.7.dist-info/top_level.txt
glass_web-0.0.7.dist-info/RECORD
